TwoSampleHC/TwoSampleHC.py
TwoSampleHC/__init__.py
TwoSampleHC/hc_vals.py
TwoSampleHC-0.4.0.dist-info/LICENSE
TwoSampleHC-0.4.0.dist-info/METADATA
TwoSampleHC-0.4.0.dist-info/WHEEL
TwoSampleHC-0.4.0.dist-info/top_level.txt
TwoSampleHC-0.4.0.dist-info/RECORD
