Metadata-Version: 2.1
Name: TwoSampleHC
Version: 0.4.0
Summary: Several two-samples tests for contingency tables with counts data
Home-page: https://github.com/alonkipnis/TwoSampleHC
Download-URL: https://github.com/alonkipnis/TwoSampleHC
Author: Alon Kipnis
Author-email: alonkipnis@gmail.com
Classifier: Programming Language :: Python :: 3
Classifier: License :: OSI Approved :: MIT License
Classifier: Operating System :: OS Independent
Requires-Python: >=3.6
License-File: LICENSE
Requires-Dist: numpy>=1.6
Requires-Dist: scipy
